consensual_http/__init__.py
consensual_http/communication.py
consensual_http/core/__init__.py
consensual_http/core/consts.py
consensual_http/core/hints.py
consensual_http/core/receiver.py
consensual_http/core/result.py
consensual_http/core/sender.py
consensual_http-0.1.0.dist-info/LICENSE
consensual_http-0.1.0.dist-info/METADATA
consensual_http-0.1.0.dist-info/WHEEL
consensual_http-0.1.0.dist-info/top_level.txt
consensual_http-0.1.0.dist-info/RECORD
